Metadata-Version: 2.1
Name: wcao_first_package
Version: 0.0
Summary: Gaussian and Binomial distributions
Author-email: wenleicao@gmail.com
